cnvrg_endpoint_binary/__init__.py
cnvrg_endpoint_binary/custom_thread.py
cnvrg_endpoint_binary/endpoint_binary.py
cnvrg_endpoint_binary/endpoint_thread.py
cnvrg_endpoint_binary-0.0.3.dist-info/LICENSE.txt
cnvrg_endpoint_binary-0.0.3.dist-info/METADATA
cnvrg_endpoint_binary-0.0.3.dist-info/WHEEL
cnvrg_endpoint_binary-0.0.3.dist-info/top_level.txt
cnvrg_endpoint_binary-0.0.3.dist-info/RECORD
