Metadata-Version: 2.1
Name: cnvrg-endpoint-binary
Version: 0.0.3
Summary: Add a short description here!
Home-page: https://github.com/nctiggy/cnvrg_endpoint_binary
Author: Craig Smith
Author-email: nctiggy@gmail.com
License: MIT
Project-URL: Documentation, https://pyscaffold.org/
Platform: any
Classifier: Development Status :: 4 - Beta
Classifier: Programming Language :: Python
License-File: LICENSE.txt
Requires-Dist: cnvrgv2
Requires-Dist: importlib-metadata ; python_version < "3.8"
Provides-Extra: testing
Requires-Dist: setuptools ; extra == 'testing'
Requires-Dist: pytest ; extra == 'testing'
Requires-Dist: pytest-cov ; extra == 'testing'
